privateai_client/__about__.py
privateai_client/__init__.py
privateai_client/objects.py
privateai_client/pai_client.py
privateai_client/components/__init__.py
privateai_client/components/pai_requests.py
privateai_client/components/pai_responses.py
privateai_client/components/pai_uris.py
privateai_client/components/request_objects.py
privateai_client/post_processing/__init__.py
privateai_client/post_processing/post_processing.py
privateai_client/post_processing/processors/__init__.py
privateai_client/post_processing/processors/default.py
privateai_client/post_processing/processors/fuzzy_match.py
privateai_client/tests/.env
privateai_client/tests/.env.example
privateai_client/tests/.gitignore
privateai_client/tests/__init__.py
privateai_client/tests/test_client.py
privateai_client/tests/test_integration.py
privateai_client/tests/test_post_processing.py
privateai_client/tests/test_request_objects.py
privateai_client/tests/test_files/demo-sequence.dcm
privateai_client/tests/test_files/demo-simple.pptx
privateai_client/tests/test_files/simpsons_wiki.txt
privateai_client/tests/test_files/test_audio.mp3
privateai_client/tests/test_files/test_image.jpg
privateai_client-4.2.1.dist-info/METADATA
privateai_client-4.2.1.dist-info/WHEEL
privateai_client-4.2.1.dist-info/licenses/LICENSE
privateai_client-4.2.1.dist-info/RECORD
