Metadata-Version: 2.4
Name: privateai_client
Version: 4.2.1
Summary: A thin client for communicating with the Private AI de-identication API.
Project-URL: Homepage, https://github.com/privateai/pai-thin-client/
Project-URL: Bug Tracker, https://github.com/privateai/pai-thin-client/issues
Project-URL: Changelog, https://github.com/privateai/pai-thin-client/blob/main/CHANGELOG.md
Project-URL: Contributing, https://github.com/privateai/pai-thin-client/blob/main/CONTRIBUTING.md
Author-email: Adam Guiducci <adam.guiducci@private-ai.com>, Bryan Bell-Smith <bryan.bellsmith@private-ai.com>
License-File: LICENSE
Classifier: License :: OSI Approved :: MIT License
Classifier: Operating System :: OS Independent
Classifier: Programming Language :: Python :: 3
Requires-Python: >=3.8
Requires-Dist: pyxdameraulevenshtein~=1.8.0
Requires-Dist: requests~=2.32.3
